{
  "player_y": 99728.46999999986,
  "distance_travelled": 192.53000000014435,
  "next_event_at": 436.0,
  "player_gender": "male",
  "party_slots_names": [
    "RTokenRanger1.png",
    "FTokenPaladin1.png",
    null,
    null,
    "StarterTokenBarbarian5.png",
    "FTokenBarbarian1.png"
  ],
  "party_vessel_stats": [
    {
      "name": "RVesselRanger1.png",
      "class_name": "Ranger",
      "level": 1,
      "abilities": {
        "STR": 10,
        "DEX": 15,
        "CON": 13,
        "INT": 7,
        "WIS": 14,
        "CHA": 8
      },
      "mods": {
        "STR": 0,
        "DEX": 2,
        "CON": 1,
        "INT": -2,
        "WIS": 2,
        "CHA": -1
      },
      "prof": 2,
      "ac": 15,
      "hp": 11,
      "initiative": 2,
      "attack_stat": "DEX",
      "attack_bonus": 4,
      "notes": "Generated from asset name",
      "current_hp": 11
    },
    {
      "name": "FVesselPaladin1.png",
      "class_name": "Paladin",
      "level": 1,
      "abilities": {
        "STR": 15,
        "DEX": 11,
        "CON": 13,
        "INT": 11,
        "WIS": 11,
        "CHA": 14
      },
      "mods": {
        "STR": 2,
        "DEX": 0,
        "CON": 1,
        "INT": 0,
        "WIS": 0,
        "CHA": 2
      },
      "prof": 2,
      "ac": 14,
      "hp": 11,
      "initiative": 0,
      "attack_stat": "STR",
      "attack_bonus": 4,
      "notes": "Generated from asset name",
      "current_hp": 11,
      "custom_name": "Balls"
    },
    null,
    null,
    {
      "name": "StarterBarbarian5",
      "class_name": "Barbarian",
      "level": 1,
      "abilities": {
        "STR": 16,
        "DEX": 15,
        "CON": 15,
        "INT": 14,
        "WIS": 14,
        "CHA": 13
      },
      "mods": {
        "STR": 3,
        "DEX": 2,
        "CON": 2,
        "INT": 2,
        "WIS": 2,
        "CHA": 1
      },
      "prof": 2,
      "ac": 16,
      "hp": 14,
      "initiative": 2,
      "attack_stat": "STR",
      "attack_bonus": 5,
      "notes": "Generated from asset name",
      "current_hp": 14
    },
    {
      "name": "FTokenBarbarian1.png",
      "class_name": "FTokenBarbarian",
      "level": 1,
      "abilities": {
        "STR": 16,
        "DEX": 13,
        "CON": 11,
        "INT": 9,
        "WIS": 9,
        "CHA": 8
      },
      "mods": {
        "STR": 3,
        "DEX": 1,
        "CON": 0,
        "INT": -1,
        "WIS": -1,
        "CHA": -1
      },
      "prof": 2,
      "ac": 12,
      "hp": 8,
      "initiative": 1,
      "attack_stat": "STR",
      "attack_bonus": 5,
      "notes": "Generated from asset name",
      "current_hp": 8
    }
  ],
  "rivals_on_map": [],
  "vessels_on_map": [
    {
      "side": "left",
      "x": 1101.0,
      "y": 97280.66999999991
    }
  ],
  "merchants_on_map": [],
  "taverns_on_map": [],
  "monsters_on_map": [],
  "inventory": {
    "scroll_of_command": 5,
    "scroll_of_sealing": 5,
    "scroll_of_subjugation": 3,
    "scroll_of_eternity": 3,
    "scroll_of_healing": 3,
    "scroll_of_regeneration": 2,
    "scroll_of_revivity": 1,
    "rations": 1,
    "alcohol": 1
  },
  "total_points": 0,
  "gold": 100,
  "silver": 0,
  "bronze": 0,
  "book_of_bound_discovered": [
    "StarterBarbarian5"
  ],
  "archives": [],
  "active_buffs": [
    {
      "tier": "Common",
      "id": 1,
      "name": "Common1",
      "image_path": "Assets\\Blessings\\Common1.png"
    }
  ],
  "buffs_history": [
    {
      "tier": "Common",
      "id": 1,
      "name": "Common1",
      "image_path": "Assets\\Blessings\\Common1.png"
    }
  ],
  "first_overworld_blessing_given": true,
  "saved_in_tavern": false
}